djangoiot/__init__.py
djangoiot/admin.py
djangoiot/apps.py
djangoiot/goiotbackend-linux-0.0.7
djangoiot/goiotbackend-mac-0.0.7
djangoiot/goiotbackend-win-0.0.7.exe
djangoiot/models.py
djangoiot/tests.py
djangoiot/views.py
djangoiot/migrations/__init__.py
djangoiot-0.0.7.dist-info/LICENSE.txt
djangoiot-0.0.7.dist-info/METADATA
djangoiot-0.0.7.dist-info/WHEEL
djangoiot-0.0.7.dist-info/top_level.txt
djangoiot-0.0.7.dist-info/RECORD
